aws_service_availability/__init__.py
aws_service_availability/__main__.py
aws_service_availability/scraper.py
aws_service_availability-1.0.2.dist-info/entry_points.txt
aws_service_availability-1.0.2.dist-info/LICENSE
aws_service_availability-1.0.2.dist-info/WHEEL
aws_service_availability-1.0.2.dist-info/METADATA
aws_service_availability-1.0.2.dist-info/RECORD
